{"cookies": [], "origins": [{"origin": "https://nikita-filonov.github.io", "localStorage": [{"name": "persist:users", "value": "{\"user\":\"{\\\"id\\\":\\\"d22f81cd-a7b3-4102-b35b-81057e3ca12e\\\",\\\"email\\\":\\\"user.name@gmail.com\\\",\\\"username\\\":\\\"username\\\",\\\"password\\\":\\\"password\\\"}\",\"users\":\"[{\\\"id\\\":\\\"d22f81cd-a7b3-4102-b35b-81057e3ca12e\\\",\\\"email\\\":\\\"user.name@gmail.com\\\",\\\"username\\\":\\\"username\\\",\\\"password\\\":\\\"password\\\"}]\",\"_persist\":\"{\\\"version\\\":-1,\\\"rehydrated\\\":true}\"}"}, {"name": "persist:courses", "value": "{\"course\":\"{\\\"id\\\":\\\"\\\",\\\"title\\\":\\\"\\\",\\\"userId\\\":\\\"\\\",\\\"maxScore\\\":0,\\\"minScore\\\":0,\\\"exercises\\\":[],\\\"description\\\":\\\"\\\",\\\"previewImage\\\":null,\\\"estimatedTime\\\":\\\"\\\"}\",\"courses\":\"[]\",\"_persist\":\"{\\\"version\\\":-1,\\\"rehydrated\\\":true}\"}"}]}]}